__init__.py
shipping6DOF/baseclasses/__init__.py
shipping6DOF/baseclasses/abstract_matrix.py
shipping6DOF/baseclasses/metaclasses.py
shipping6DOF/rotationclasses/__init__.py
shipping6DOF/rotationclasses/originandaxis.py
shipping6DOF/rotationclasses/quaternion.py
shipping6DOF/rotationclasses/rotation_vector.py
shipping6DOF/utils/__init__.py
shipping6DOF/utils/utils.py
shipping6dof-0.1.4.dist-info/licenses/LICENSE
shipping6dof-0.1.4.dist-info/METADATA
shipping6dof-0.1.4.dist-info/WHEEL
shipping6dof-0.1.4.dist-info/top_level.txt
shipping6dof-0.1.4.dist-info/RECORD
