Metadata-Version: 2.4
Name: shipping6DOF
Version: 0.1.4
Summary: A simple package for the calculation of rotations, quaternions, and Euler angles, for planes and vectors.
Author-email: Santiago Lopez Castano <santilopez01@gmail.com>
License-Expression: MIT
Project-URL: Homepage, https://something.github.com
Requires-Python: >=3.13
License-File: LICENSE
Requires-Dist: numpy>=2.0.0
Requires-Dist: pytest>=8.0.0
Dynamic: license-file
